git_flash/__init__.py
git_flash/client.py
git_flash/server.py
git_flash-0.2.4.dist-info/METADATA
git_flash-0.2.4.dist-info/WHEEL
git_flash-0.2.4.dist-info/entry_points.txt
git_flash-0.2.4.dist-info/licenses/LICENSE
git_flash-0.2.4.dist-info/RECORD
