Metadata-Version: 2.4
Name: git-flash
Version: 0.2.4
Summary: An AI assistant for git operations using FastMCP.
Author-email: Alosh Denny <aloshdenny@gmail.com>
License-File: LICENSE
Requires-Python: >=3.10
Requires-Dist: fastmcp
Requires-Dist: google-generativeai
Requires-Dist: python-dotenv
Requires-Dist: rich
Requires-Dist: typer
